dynite/__init__.py
dynite/client.py
dynite/exceptions.py
dynite/py.typed
dynite-0.2.0.dist-info/METADATA
dynite-0.2.0.dist-info/WHEEL
dynite-0.2.0.dist-info/licenses/LICENSE
dynite-0.2.0.dist-info/RECORD
