Metadata-Version: 2.4
Name: dynite
Version: 0.2.0
Summary: A python client for Business Central OData API.
Author-email: prabhuakshay <akshay.prabhu.mulki@gmail.com>
License-File: LICENSE
Requires-Python: >=3.13
Requires-Dist: requests>=2.32.5
